pmr2.wfctrl-0.8.0-py3.11-nspkg.pth
pmr2/wfctrl/__init__.py
pmr2/wfctrl/cmd.py
pmr2/wfctrl/core.py
pmr2/wfctrl/utils.py
pmr2/wfctrl/testing/__init__.py
pmr2/wfctrl/testing/base.py
pmr2_wfctrl-0.8.0.dist-info/METADATA
pmr2_wfctrl-0.8.0.dist-info/WHEEL
pmr2_wfctrl-0.8.0.dist-info/namespace_packages.txt
pmr2_wfctrl-0.8.0.dist-info/top_level.txt
pmr2_wfctrl-0.8.0.dist-info/RECORD
