Metadata-Version: 2.4
Name: pmr2.wfctrl
Version: 0.8.0
Summary: Workflow controller
Home-page: http://github.com/PMR/pmr2.wfctrl
Author: 
Author-email: 
License: gpl
Classifier: Programming Language :: Python
Requires-Dist: setuptools
Provides-Extra: dulwich
Requires-Dist: dulwich>=0.20.46; extra == "dulwich"
Dynamic: classifier
Dynamic: description
Dynamic: home-page
Dynamic: keywords
Dynamic: license
Dynamic: provides-extra
Dynamic: requires-dist
Dynamic: summary
